rpycolors/__init__.py
rpycolors-0.0.5.dist-info/METADATA
rpycolors-0.0.5.dist-info/WHEEL
rpycolors-0.0.5.dist-info/top_level.txt
rpycolors-0.0.5.dist-info/RECORD
