Metadata-Version: 2.1
Name: rpycolors
Version: 0.0.5
Summary: Colors on terminal
Home-page: https://github.com/ReddyyZ/PyColors
Author: ReddyyZ
Author-email: arthurc.oli.whitehat@gmail.com
License: UNKNOWN
Platform: UNKNOWN
Classifier: Programming Language :: Python :: 3
Classifier: License :: OSI Approved :: MIT License
Classifier: Operating System :: OS Independent
Requires-Python: >=3.6
